README.md
setup.py
src/medicalworkers.py
src/medicalworkers.egg-info/PKG-INFO
src/medicalworkers.egg-info/SOURCES.txt
src/medicalworkers.egg-info/dependency_links.txt
src/medicalworkers.egg-info/entry_points.txt
src/medicalworkers.egg-info/top_level.txt