Metadata-Version: 2.1
Name: medicalworkers
Version: 0.0.2
Summary: A package for visualizing medical workers of up to 4 countries
Home-page: https://github.com/kanako68/medicalworkers
Author: kanako akamine
Author-email: s2022068@stu.musashino-u.ac.jp
License: UNKNOWN
Project-URL: Bug Tracker, https://github.com/kanako68/medicalworkers
Platform: UNKNOWN
Classifier: Programming Language :: Python :: 3
Classifier: License :: OSI Approved :: MIT License
Classifier: Operating System :: OS Independent
Requires-Python: >=3.7
